Workbook

Sheet Read Me
A1: How to Use This Workbook
A2: Designed as a portfolio artifact for the 2027 Morgan Stanley Investment Management Summer Analyst – Strategic Functions application.
A4: Workflow
A6: 1. Review the peer set | B6: Product Landscape contains the five-fund EM competitor scan and the peer-set economics.
A7: 2. Review the risk analysis | B7: Risk Analytics and Correlation Matrix contain the formula-driven three-year calculations.
A8: 3. Reproduce the analysis | B8: Run analysis.py to rebuild the risk metrics, correlation CSV, and four charts from the bundled source data.
A9: 4. Read the strategy case | B9: Strategy Case connects the competitive evidence and risk results to the hypothetical product concept.
A10: 5. Use the project publicly | B10: Use the workbook, README, charts, and concise resume bullets as the portfolio package.
A13: Important Note
A15: The embedded results use month-end adjusted prices from Aug 2023 through Aug 2026. Month-end drawdown can understate intramonth losses, and the historical VaR estimate uses only 36 monthly returns. Treat these as portfolio-project diagnostics rather than production risk estimates; refresh current product fields before an interview.

Sheet Dashboard
A1: ETF Product Strategy & Risk Analytics
A2: Morgan Stanley Investment Management – Strategic Functions portfolio project | Competitive landscape + quantitative risk framework
A4: Executive Snapshot
A6: Selected Peer AUM | D6: Lowest Expense Ratio | G6: Median Expense Ratio | J6: Largest Fund AUM
A7: =SUM('Product Landscape'!F6:F10) | D7: =MIN('Product Landscape'!G6:G10) | G7: =MEDIAN('Product Landscape'!G6:G10) | J7: =MAX('Product Landscape'!F6:F10)
A10: What the Combined Data Says
A12: • Broad EM beta is already fee-compressed: four of the five selected peers charge 0.06%–0.09%, so price alone is a weak entry strategy.
A13: • EEM returned 83.8% over Aug 2023–Aug 2026 (22.5% CAGR) with 15.4% annualized volatility and 0.79 beta to SPY.
A14: • Cross-asset results reinforce the value of risk architecture: GLD had ~0.02 correlation with SPY, while high yield remained strongly equity-sensitive.
A15: • Product implication: test a differentiated systematic EM proposition with quality, concentration, liquidity, and drawdown controls rather than another broad-beta clone.
A17: Illustrative Product Recommendation
A19: Working concept: MSIM Emerging Markets Quality & Risk ETF (hypothetical)
A20: Positioning: differentiated systematic exposure rather than another fee-led broad-market clone. Portfolio design: profitability / balance-sheet quality signals plus country, sector, liquidity, and concentration controls. Commercial test: validate demand, fee tolerance, distribution fit, tracking error, capacity, and implementation costs before launch.
A25: Project Deliverables
A27: 1 | B27: Market / competitor scan | C27: Compare issuer, benchmark, AUM, fees, breadth, and positioning.
A28: 2 | B28: Quantitative risk engine | C28: Python pipeline for return, volatility, Sharpe, Sortino, drawdown, VaR, beta, and correlations.
A29: 3 | B29: Excel decision dashboard | C29: Present product economics and analytical outputs in an interview-friendly format.
A30: 4 | B30: Product strategy case | C30: Translate the data into a launch / positioning recommendation and implementation considerations.

Sheet Product Landscape
A1: Emerging Markets ETF Competitive Landscape
A2: Current public product snapshot; figures are drawn from issuer pages and intentionally emphasize business/product structure, not investment recommendations.
A4: Selected Peer Set
A5: Ticker | B5: Fund | C5: Issuer | D5: Benchmark | E5: Style | F5: AUM ($bn) | G5: Expense Ratio | H5: Holdings | I5: Inception | J5: Field as-of dates | K5: Selected-set AUM Share | L5: Fee vs Median | M5: Positioning | N5: Source URL
A6: EEM | B6: iShares MSCI Emerging Markets ETF | C6: iShares / BlackRock | D6: MSCI Emerging Markets Index (Net) | E6: Passive | Large/Mid Cap | F6: 31.274778 | G6: 0.0072 | H6: 1185 | I6: 2003-04-07 | J6: AUM 2026-09-18; holdings 2026-09-17; fee Current prospectus (accessed 2026-09-19) | K6: =F6/$F$12 | L6: =G6-$G$12 | M6: Legacy, highly liquid trading vehicle; materially higher fee. | N6: https://www.ishares.com/us/products/239637/ishares-msci-emerging-markets-etf
A7: IEMG | B7: iShares Core MSCI Emerging Markets ETF | C7: iShares / BlackRock | D7: MSCI Emerging Markets Investable Market Index (USD) (Net) | E7: Passive | All Cap | F7: 161.78441 | G7: 0.0009 | H7: 2860 | I7: 2012-10-18 | J7: AUM 2026-09-18; holdings 2026-09-17; fee Current prospectus (accessed 2026-09-19) | K7: =F7/$F$12 | L7: =G7-$G$12 | M7: Low-cost core exposure with very large scale and small-cap inclusion. | N7: https://www.ishares.com/us/products/244050/ishares-core-msci-emerging-markets-etf
A8: VWO | B8: Vanguard FTSE Emerging Markets ETF | C8: Vanguard | D8: FTSE Emerging Markets All Cap China A Inclusion Index | E8: Passive | All Cap | F8: 127.3 | G8: 0.0006 | H8: 6338 | I8: 2005-03-04 | J8: AUM 2026-08-31; holdings 2026-07-31; fee 2026-02-27 | K8: =F8/$F$12 | L8: =G8-$G$12 | M8: Low-cost, extremely broad all-cap exposure and significant scale. | N8: https://advisors.vanguard.com/investments/products/vwo/vanguard-ftse-emerging-markets-etf
A9: SPEM | B9: State Street SPDR Portfolio Emerging Markets ETF | C9: State Street | D9: S&P Emerging BMI Index | E9: Passive | Broad Market | F9: 17.49008 | G9: 0.0007 | H9: 2980 | I9: 2007-03-20 | J9: AUM 2026-09-16; holdings 2026-09-16; fee Fund information as of 2026-09-17 | K9: =F9/$F$12 | L9: =G9-$G$12 | M9: Low-cost diversified beta exposure using the S&P emerging-markets universe. | N9: https://www.ssga.com/us/en/individual/etfs/state-street-spdr-portfolio-emerging-markets-etf-spem
A10: SCHE | B10: Schwab Emerging Markets Equity ETF | C10: Schwab | D10: FTSE Emerging Index (Net) | E10: Passive | Large/Mid Cap | F10: 12.892369 | G10: 0.0006 | H10: 2219 | I10: 2010-01-14 | J10: AUM 2026-09-18; holdings 2026-09-17; fee 0.06% effective 2026-06-11; page accessed 2026-09-19 | K10: =F10/$F$12 | L10: =G10-$G$12 | M10: Low-cost core large/mid-cap exposure with straightforward implementation. | N10: https://www.schwabassetmanagement.com/products/sche
E12: Peer-set total / median | F12: =SUM(F6:F10) | G12: =MEDIAN(G6:G10) | H12: =SUM(H6:H10)
A15: Strategic Read-Through
A17: • Pricing pressure: four peers cluster at 0.06%–0.09%, making an undifferentiated passive launch difficult to justify on fee.
A18: • Scale advantage: IEMG and VWO have substantially greater AUM than the rest of the selected peer set, reinforcing distribution and liquidity advantages.
A19: • Product architecture matters: benchmarks differ in market-cap coverage and index families, showing that “emerging markets” is not a single standardized exposure.
A20: • Entry thesis: differentiated active/systematic exposure should be evaluated before launching another broad beta product.

Sheet Analysis Results
A1: Analysis Results | Product Strategy + Multi-Asset Risk
A2: Three-year window: Aug 2023–Aug 2026 | Month-end adjusted prices | Historical analysis, not an investment recommendation.
A4: Key Findings
A6: 1 | B6: EEM: 22.5% CAGR with 15.4% volatility and 0.79x beta to SPY — strong participation, but not a low-risk substitute for developed-market equity.
A7: 2 | B7: SPY vs QQQ: QQQ added 3.6% of CAGR, while annualized volatility was 4.8% higher. The return premium came with materially more risk.
A8: 3 | B8: GLD: 0.02 correlation with SPY, yet a 23.8% month-end drawdown. Diversification benefit and standalone risk are separate questions.
A9: 4 | B9: Fixed income: AGG and LQD reduced volatility; HYG earned more but its 0.77 correlation with SPY shows meaningful risk-asset sensitivity.
A10: 5 | B10: Product read-through: broad EM fees are compressed, so the more defensible entry point is differentiated systematic exposure rather than another low-cost beta clone.
A11: Decision takeaway: the analysis supports testing differentiated product architecture, not competing on fee alone.
A12: Charts

Sheet Risk Analytics
A1: Quantitative Risk Analytics Framework
A2: Three-year analysis using month-end adjusted prices from Aug 2023 through Aug 2026. Metrics are formula-driven; VaR is monthly, and drawdown is based on month-end observations.
A4: Multi-Asset ETF Universe
A5: Ticker | B5: Exposure | C5: Fund | D5: Total Return | E5: CAGR | F5: Ann. Volatility | G5: Sharpe | H5: Sortino | I5: Max Drawdown | J5: 95% Hist. VaR | K5: Beta vs SPY
A6: SPY | B6: U.S. Large Cap | C6: SPDR S&P 500 ETF Trust | D6: ='Monthly Prices'!B41/'Monthly Prices'!B5-1 | E6: =('Monthly Prices'!B41/'Monthly Prices'!B5)^(12/COUNT('Monthly Returns'!B5:B40))-1 | F6: =STDEV.S('Monthly Returns'!B5:B40)*SQRT(12) | G6: =(AVERAGE('Monthly Returns'!B5:B40)-AVERAGE('Monthly Returns'!$L$5:$L$40))/STDEV.S('Monthly Returns'!B5:B40)*SQRT(12) | H6: =IFERROR(((AVERAGE('Monthly Returns'!B5:B40)-AVERAGE('Monthly Returns'!$L$5:$L$40))*12)/(SQRT(SUMSQ('Monthly Returns'!M5:M40)/COUNT('Monthly Returns'!M5:M40))*SQRT(12)),0) | I6: =MIN('Drawdown Calc'!B5:B41) | J6: =-PERCENTILE.INC('Monthly Returns'!B5:B40,0.05) | K6: =COVARIANCE.S('Monthly Returns'!B5:B40,'Monthly Returns'!$B$5:$B$40)/VAR.S('Monthly Returns'!$B$5:$B$40)
A7: QQQ | B7: U.S. Growth / Tech | C7: Invesco QQQ Trust | D7: ='Monthly Prices'!C41/'Monthly Prices'!C5-1 | E7: =('Monthly Prices'!C41/'Monthly Prices'!C5)^(12/COUNT('Monthly Returns'!C5:C40))-1 | F7: =STDEV.S('Monthly Returns'!C5:C40)*SQRT(12) | G7: =(AVERAGE('Monthly Returns'!C5:C40)-AVERAGE('Monthly Returns'!$L$5:$L$40))/STDEV.S('Monthly Returns'!C5:C40)*SQRT(12) | H7: =IFERROR(((AVERAGE('Monthly Returns'!C5:C40)-AVERAGE('Monthly Returns'!$L$5:$L$40))*12)/(SQRT(SUMSQ('Monthly Returns'!N5:N40)/COUNT('Monthly Returns'!N5:N40))*SQRT(12)),0) | I7: =MIN('Drawdown Calc'!C5:C41) | J7: =-PERCENTILE.INC('Monthly Returns'!C5:C40,0.05) | K7: =COVARIANCE.S('Monthly Returns'!C5:C40,'Monthly Returns'!$B$5:$B$40)/VAR.S('Monthly Returns'!$B$5:$B$40)
A8: IWM | B8: U.S. Small Cap | C8: iShares Russell 2000 ETF | D8: ='Monthly Prices'!D41/'Monthly Prices'!D5-1 | E8: =('Monthly Prices'!D41/'Monthly Prices'!D5)^(12/COUNT('Monthly Returns'!D5:D40))-1 | F8: =STDEV.S('Monthly Returns'!D5:D40)*SQRT(12) | G8: =(AVERAGE('Monthly Returns'!D5:D40)-AVERAGE('Monthly Returns'!$L$5:$L$40))/STDEV.S('Monthly Returns'!D5:D40)*SQRT(12) | H8: =IFERROR(((AVERAGE('Monthly Returns'!D5:D40)-AVERAGE('Monthly Returns'!$L$5:$L$40))*12)/(SQRT(SUMSQ('Monthly Returns'!O5:O40)/COUNT('Monthly Returns'!O5:O40))*SQRT(12)),0) | I8: =MIN('Drawdown Calc'!D5:D41) | J8: =-PERCENTILE.INC('Monthly Returns'!D5:D40,0.05) | K8: =COVARIANCE.S('Monthly Returns'!D5:D40,'Monthly Returns'!$B$5:$B$40)/VAR.S('Monthly Returns'!$B$5:$B$40)
A9: EFA | B9: Developed ex-U.S. | C9: iShares MSCI EAFE ETF | D9: ='Monthly Prices'!E41/'Monthly Prices'!E5-1 | E9: =('Monthly Prices'!E41/'Monthly Prices'!E5)^(12/COUNT('Monthly Returns'!E5:E40))-1 | F9: =STDEV.S('Monthly Returns'!E5:E40)*SQRT(12) | G9: =(AVERAGE('Monthly Returns'!E5:E40)-AVERAGE('Monthly Returns'!$L$5:$L$40))/STDEV.S('Monthly Returns'!E5:E40)*SQRT(12) | H9: =IFERROR(((AVERAGE('Monthly Returns'!E5:E40)-AVERAGE('Monthly Returns'!$L$5:$L$40))*12)/(SQRT(SUMSQ('Monthly Returns'!P5:P40)/COUNT('Monthly Returns'!P5:P40))*SQRT(12)),0) | I9: =MIN('Drawdown Calc'!E5:E41) | J9: =-PERCENTILE.INC('Monthly Returns'!E5:E40,0.05) | K9: =COVARIANCE.S('Monthly Returns'!E5:E40,'Monthly Returns'!$B$5:$B$40)/VAR.S('Monthly Returns'!$B$5:$B$40)
A10: EEM | B10: Emerging Markets | C10: iShares MSCI Emerging Markets ETF | D10: ='Monthly Prices'!F41/'Monthly Prices'!F5-1 | E10: =('Monthly Prices'!F41/'Monthly Prices'!F5)^(12/COUNT('Monthly Returns'!F5:F40))-1 | F10: =STDEV.S('Monthly Returns'!F5:F40)*SQRT(12) | G10: =(AVERAGE('Monthly Returns'!F5:F40)-AVERAGE('Monthly Returns'!$L$5:$L$40))/STDEV.S('Monthly Returns'!F5:F40)*SQRT(12) | H10: =IFERROR(((AVERAGE('Monthly Returns'!F5:F40)-AVERAGE('Monthly Returns'!$L$5:$L$40))*12)/(SQRT(SUMSQ('Monthly Returns'!Q5:Q40)/COUNT('Monthly Returns'!Q5:Q40))*SQRT(12)),0) | I10: =MIN('Drawdown Calc'!F5:F41) | J10: =-PERCENTILE.INC('Monthly Returns'!F5:F40,0.05) | K10: =COVARIANCE.S('Monthly Returns'!F5:F40,'Monthly Returns'!$B$5:$B$40)/VAR.S('Monthly Returns'!$B$5:$B$40)
A11: AGG | B11: Core U.S. Bonds | C11: iShares Core U.S. Aggregate Bond ETF | D11: ='Monthly Prices'!G41/'Monthly Prices'!G5-1 | E11: =('Monthly Prices'!G41/'Monthly Prices'!G5)^(12/COUNT('Monthly Returns'!G5:G40))-1 | F11: =STDEV.S('Monthly Returns'!G5:G40)*SQRT(12) | G11: =(AVERAGE('Monthly Returns'!G5:G40)-AVERAGE('Monthly Returns'!$L$5:$L$40))/STDEV.S('Monthly Returns'!G5:G40)*SQRT(12) | H11: =IFERROR(((AVERAGE('Monthly Returns'!G5:G40)-AVERAGE('Monthly Returns'!$L$5:$L$40))*12)/(SQRT(SUMSQ('Monthly Returns'!R5:R40)/COUNT('Monthly Returns'!R5:R40))*SQRT(12)),0) | I11: =MIN('Drawdown Calc'!G5:G41) | J11: =-PERCENTILE.INC('Monthly Returns'!G5:G40,0.05) | K11: =COVARIANCE.S('Monthly Returns'!G5:G40,'Monthly Returns'!$B$5:$B$40)/VAR.S('Monthly Returns'!$B$5:$B$40)
A12: LQD | B12: Investment Grade Credit | C12: iShares iBoxx $ Investment Grade Corporate Bond ETF | D12: ='Monthly Prices'!H41/'Monthly Prices'!H5-1 | E12: =('Monthly Prices'!H41/'Monthly Prices'!H5)^(12/COUNT('Monthly Returns'!H5:H40))-1 | F12: =STDEV.S('Monthly Returns'!H5:H40)*SQRT(12) | G12: =(AVERAGE('Monthly Returns'!H5:H40)-AVERAGE('Monthly Returns'!$L$5:$L$40))/STDEV.S('Monthly Returns'!H5:H40)*SQRT(12) | H12: =IFERROR(((AVERAGE('Monthly Returns'!H5:H40)-AVERAGE('Monthly Returns'!$L$5:$L$40))*12)/(SQRT(SUMSQ('Monthly Returns'!S5:S40)/COUNT('Monthly Returns'!S5:S40))*SQRT(12)),0) | I12: =MIN('Drawdown Calc'!H5:H41) | J12: =-PERCENTILE.INC('Monthly Returns'!H5:H40,0.05) | K12: =COVARIANCE.S('Monthly Returns'!H5:H40,'Monthly Returns'!$B$5:$B$40)/VAR.S('Monthly Returns'!$B$5:$B$40)
A13: HYG | B13: High Yield Credit | C13: iShares iBoxx $ High Yield Corporate Bond ETF | D13: ='Monthly Prices'!I41/'Monthly Prices'!I5-1 | E13: =('Monthly Prices'!I41/'Monthly Prices'!I5)^(12/COUNT('Monthly Returns'!I5:I40))-1 | F13: =STDEV.S('Monthly Returns'!I5:I40)*SQRT(12) | G13: =(AVERAGE('Monthly Returns'!I5:I40)-AVERAGE('Monthly Returns'!$L$5:$L$40))/STDEV.S('Monthly Returns'!I5:I40)*SQRT(12) | H13: =IFERROR(((AVERAGE('Monthly Returns'!I5:I40)-AVERAGE('Monthly Returns'!$L$5:$L$40))*12)/(SQRT(SUMSQ('Monthly Returns'!T5:T40)/COUNT('Monthly Returns'!T5:T40))*SQRT(12)),0) | I13: =MIN('Drawdown Calc'!I5:I41) | J13: =-PERCENTILE.INC('Monthly Returns'!I5:I40,0.05) | K13: =COVARIANCE.S('Monthly Returns'!I5:I40,'Monthly Returns'!$B$5:$B$40)/VAR.S('Monthly Returns'!$B$5:$B$40)
A14: GLD | B14: Gold | C14: SPDR Gold Shares | D14: ='Monthly Prices'!J41/'Monthly Prices'!J5-1 | E14: =('Monthly Prices'!J41/'Monthly Prices'!J5)^(12/COUNT('Monthly Returns'!J5:J40))-1 | F14: =STDEV.S('Monthly Returns'!J5:J40)*SQRT(12) | G14: =(AVERAGE('Monthly Returns'!J5:J40)-AVERAGE('Monthly Returns'!$L$5:$L$40))/STDEV.S('Monthly Returns'!J5:J40)*SQRT(12) | H14: =IFERROR(((AVERAGE('Monthly Returns'!J5:J40)-AVERAGE('Monthly Returns'!$L$5:$L$40))*12)/(SQRT(SUMSQ('Monthly Returns'!U5:U40)/COUNT('Monthly Returns'!U5:U40))*SQRT(12)),0) | I14: =MIN('Drawdown Calc'!J5:J41) | J14: =-PERCENTILE.INC('Monthly Returns'!J5:J40,0.05) | K14: =COVARIANCE.S('Monthly Returns'!J5:J40,'Monthly Returns'!$B$5:$B$40)/VAR.S('Monthly Returns'!$B$5:$B$40)
A15: VNQ | B15: U.S. Real Estate | C15: Vanguard Real Estate ETF | D15: ='Monthly Prices'!K41/'Monthly Prices'!K5-1 | E15: =('Monthly Prices'!K41/'Monthly Prices'!K5)^(12/COUNT('Monthly Returns'!K5:K40))-1 | F15: =STDEV.S('Monthly Returns'!K5:K40)*SQRT(12) | G15: =(AVERAGE('Monthly Returns'!K5:K40)-AVERAGE('Monthly Returns'!$L$5:$L$40))/STDEV.S('Monthly Returns'!K5:K40)*SQRT(12) | H15: =IFERROR(((AVERAGE('Monthly Returns'!K5:K40)-AVERAGE('Monthly Returns'!$L$5:$L$40))*12)/(SQRT(SUMSQ('Monthly Returns'!V5:V40)/COUNT('Monthly Returns'!V5:V40))*SQRT(12)),0) | I15: =MIN('Drawdown Calc'!K5:K41) | J15: =-PERCENTILE.INC('Monthly Returns'!K5:K40,0.05) | K15: =COVARIANCE.S('Monthly Returns'!K5:K40,'Monthly Returns'!$B$5:$B$40)/VAR.S('Monthly Returns'!$B$5:$B$40)
A17: Analysis Assumptions
A18: Average annualized 3M Treasury yield | B18: =AVERAGE('Risk-Free Rates'!B5:B40) | C18: Reference only. Sharpe / Sortino use each month’s FRED DGS3MO observation, converted to a monthly return.
A19: Data frequency | B19: Monthly | C19: Aug 2023–Aug 2026 full month-end observations.
A20: Return | B20: Adjusted-price total return over the selected analysis window.
A21: Methodology
A22: Sharpe | B22: Average monthly excess return over month-end DGS3MO, annualized by √12 and divided by annualized monthly-return volatility.
A23: Risk / downside | B23: Volatility is sample standard deviation of monthly returns × √12; downside deviation uses negative monthly excess returns relative to DGS3MO.
A24: Sortino | B24: Annualized average monthly excess return divided by downside deviation of monthly excess returns (positive excess months set to zero).
A25: Drawdown | B25: Largest peak-to-trough decline measured from month-end adjusted prices.
A26: VaR | B26: Historical 5th percentile of monthly returns, reported as a positive loss magnitude.
A27: Beta | B27: Covariance with SPY monthly returns divided by SPY monthly-return variance.
A28: Beta | B28: Covariance with SPY monthly returns divided by SPY monthly-return variance.

Sheet Monthly Prices
A1: Month-End Adjusted Prices | Aug 2023–Aug 2026
A2: Public monthly adjusted-price histories from Digrin; August 2026 used as the final full month. Imported data are shown in green.
A4: Date | B4: SPY | C4: QQQ | D4: IWM | E4: EFA | F4: EEM | G4: AGG | H4: LQD | I4: HYG | J4: GLD | K4: VNQ
A5: 45169 | B5: 433.86 | C5: 371.5 | D5: 182.06 | E5: 65.1 | F5: 36.47 | G5: 86.4 | H5: 92.45 | I5: 62.7 | J5: 180.02 | K5: 73.15
A6: 45199 | B6: 413.28 | C6: 352.63 | D6: 171.4 | E6: 62.73 | F6: 35.34 | G6: 84.16 | H6: 89.16 | I6: 61.69 | J6: 171.45 | K6: 67.84
A7: 45230 | B7: 404.31 | C7: 345.35 | D7: 159.55 | E7: 60.91 | F7: 34.17 | G7: 82.84 | H7: 87.01 | I7: 61.04 | J7: 184.09 | K7: 65.38
A8: 45260 | B8: 441.24 | C8: 382.71 | D8: 174.23 | E8: 65.91 | F8: 36.83 | G8: 86.65 | H8: 93.6 | I8: 64.03 | J8: 188.75 | K8: 73.28
A9: 45291 | B9: 461.38 | C9: 404.09 | D9: 195.36 | E9: 69.44 | F9: 38.15 | G9: 89.85 | H9: 98.16 | I9: 66.07 | J9: 191.17 | K9: 80.2
A10: 45322 | B10: 468.73 | C10: 411.44 | D10: 187.74 | E10: 69.13 | F10: 36.42 | G10: 89.72 | H10: 97.73 | I10: 66.15 | J10: 188.45 | K10: 76.15
A11: 45351 | B11: 493.2 | C11: 433.18 | D11: 198.3 | E11: 71.19 | F11: 37.94 | G11: 88.39 | H11: 95.84 | I11: 66.35 | J11: 189.31 | K11: 77.65
A12: 45382 | B12: 509.32 | C12: 438.7 | D12: 205.21 | E12: 73.6 | F12: 38.97 | G12: 89.19 | H12: 97.32 | I12: 67.07 | J12: 205.72 | K12: 79.17
A13: 45412 | B13: 488.79 | C13: 419.52 | D13: 191.16 | E13: 71.21 | F13: 38.89 | G13: 86.98 | H13: 94.17 | I13: 66.17 | J13: 211.87 | K13: 72.88
A14: 45443 | B14: 513.51 | C14: 445.32 | D14: 200.79 | E14: 74.81 | F14: 39.65 | G14: 88.44 | H14: 96.25 | I14: 67.25 | J14: 215.3 | K14: 76.2
A15: 45473 | B15: 531.63 | C15: 474.14 | D15: 198.53 | E15: 73.45 | F15: 40.68 | G15: 89.22 | H15: 96.82 | I15: 67.57 | J15: 215.01 | K15: 77.63
A16: 45504 | B16: 538.06 | C16: 466.18 | D16: 219.05 | E16: 75.35 | F16: 41.03 | G16: 91.38 | H16: 99.38 | I16: 69.16 | J16: 226.55 | K16: 83.79
... A41: 46265 | B41: 766.95 | C41: 716.76 | D41: 293.93 | E41: 107.43 | F41: 67.02 | G41: 97.41 | H41: 105.77 | I41: 79.38 | J41: 408.42 | K41: 96.44

Sheet Monthly Returns
A1: Monthly Return Calculations
A2: Formula-driven monthly returns from the adjusted-price series. The FRED 3-month Treasury series is aligned by month; excess-return helper columns are hidden.
A4: Date | B4: SPY | C4: QQQ | D4: IWM | E4: EFA | F4: EEM | G4: AGG | H4: LQD | I4: HYG | J4: GLD | K4: VNQ | L4: RF Monthly | M4: SPY Downside Excess | N4: QQQ Downside Excess | O4: IWM Downside Excess | P4: EFA Downside Excess | Q4: EEM Downside Excess | R4: AGG Downside Excess | S4: LQD Downside Excess | T4: HYG Downside Excess | U4: GLD Downside Excess | V4: VNQ Downside Excess
A5: 45199 | B5: =IFERROR('Monthly Prices'!B6/'Monthly Prices'!B5-1,"") | C5: =IFERROR('Monthly Prices'!C6/'Monthly Prices'!C5-1,"") | D5: =IFERROR('Monthly Prices'!D6/'Monthly Prices'!D5-1,"") | E5: =IFERROR('Monthly Prices'!E6/'Monthly Prices'!E5-1,"") | F5: =IFERROR('Monthly Prices'!F6/'Monthly Prices'!F5-1,"") | G5: =IFERROR('Monthly Prices'!G6/'Monthly Prices'!G5-1,"") | H5: =IFERROR('Monthly Prices'!H6/'Monthly Prices'!H5-1,"") | I5: =IFERROR('Monthly Prices'!I6/'Monthly Prices'!I5-1,"") | ... K5: =IFERROR('Monthly Prices'!K6/'Monthly Prices'!K5-1,"") | L5: ='Risk-Free Rates'!C5 | M5: =MIN(B5-$L5,0) | N5: =MIN(C5-$L5,0) | O5: =MIN(D5-$L5,0) | P5: =MIN(E5-$L5,0) | Q5: =MIN(F5-$L5,0) | R5: =MIN(G5-$L5,0) | S5: =MIN(H5-$L5,0) | T5: =MIN(I5-$L5,0) | ... V5: =MIN(K5-$L5,0)
A6: 45230 | B6: =IFERROR('Monthly Prices'!B7/'Monthly Prices'!B6-1,"") | C6: =IFERROR('Monthly Prices'!C7/'Monthly Prices'!C6-1,"") | D6: =IFERROR('Monthly Prices'!D7/'Monthly Prices'!D6-1,"") | E6: =IFERROR('Monthly Prices'!E7/'Monthly Prices'!E6-1,"") | F6: =IFERROR('Monthly Prices'!F7/'Monthly Prices'!F6-1,"") | G6: =IFERROR('Monthly Prices'!G7/'Monthly Prices'!G6-1,"") | H6: =IFERROR('Monthly Prices'!H7/'Monthly Prices'!H6-1,"") | I6: =IFERROR('Monthly Prices'!I7/'Monthly Prices'!I6-1,"") | ... K6: =IFERROR('Monthly Prices'!K7/'Monthly Prices'!K6-1,"") | L6: ='Risk-Free Rates'!C6 | M6: =MIN(B6-$L6,0) | N6: =MIN(C6-$L6,0) | O6: =MIN(D6-$L6,0) | P6: =MIN(E6-$L6,0) | Q6: =MIN(F6-$L6,0) | R6: =MIN(G6-$L6,0) | S6: =MIN(H6-$L6,0) | T6: =MIN(I6-$L6,0) | ... V6: =MIN(K6-$L6,0)
A7: 45260 | B7: =IFERROR('Monthly Prices'!B8/'Monthly Prices'!B7-1,"") | C7: =IFERROR('Monthly Prices'!C8/'Monthly Prices'!C7-1,"") | D7: =IFERROR('Monthly Prices'!D8/'Monthly Prices'!D7-1,"") | E7: =IFERROR('Monthly Prices'!E8/'Monthly Prices'!E7-1,"") | F7: =IFERROR('Monthly Prices'!F8/'Monthly Prices'!F7-1,"") | G7: =IFERROR('Monthly Prices'!G8/'Monthly Prices'!G7-1,"") | H7: =IFERROR('Monthly Prices'!H8/'Monthly Prices'!H7-1,"") | I7: =IFERROR('Monthly Prices'!I8/'Monthly Prices'!I7-1,"") | ... K7: =IFERROR('Monthly Prices'!K8/'Monthly Prices'!K7-1,"") | L7: ='Risk-Free Rates'!C7 | M7: =MIN(B7-$L7,0) | N7: =MIN(C7-$L7,0) | O7: =MIN(D7-$L7,0) | P7: =MIN(E7-$L7,0) | Q7: =MIN(F7-$L7,0) | R7: =MIN(G7-$L7,0) | S7: =MIN(H7-$L7,0) | T7: =MIN(I7-$L7,0) | ... V7: =MIN(K7-$L7,0)
A8: 45291 | B8: =IFERROR('Monthly Prices'!B9/'Monthly Prices'!B8-1,"") | C8: =IFERROR('Monthly Prices'!C9/'Monthly Prices'!C8-1,"") | D8: =IFERROR('Monthly Prices'!D9/'Monthly Prices'!D8-1,"") | E8: =IFERROR('Monthly Prices'!E9/'Monthly Prices'!E8-1,"") | F8: =IFERROR('Monthly Prices'!F9/'Monthly Prices'!F8-1,"") | G8: =IFERROR('Monthly Prices'!G9/'Monthly Prices'!G8-1,"") | H8: =IFERROR('Monthly Prices'!H9/'Monthly Prices'!H8-1,"") | I8: =IFERROR('Monthly Prices'!I9/'Monthly Prices'!I8-1,"") | ... K8: =IFERROR('Monthly Prices'!K9/'Monthly Prices'!K8-1,"") | L8: ='Risk-Free Rates'!C8 | M8: =MIN(B8-$L8,0) | N8: =MIN(C8-$L8,0) | O8: =MIN(D8-$L8,0) | P8: =MIN(E8-$L8,0) | Q8: =MIN(F8-$L8,0) | R8: =MIN(G8-$L8,0) | S8: =MIN(H8-$L8,0) | T8: =MIN(I8-$L8,0) | ... V8: =MIN(K8-$L8,0)
A9: 45322 | B9: =IFERROR('Monthly Prices'!B10/'Monthly Prices'!B9-1,"") | C9: =IFERROR('Monthly Prices'!C10/'Monthly Prices'!C9-1,"") | D9: =IFERROR('Monthly Prices'!D10/'Monthly Prices'!D9-1,"") | E9: =IFERROR('Monthly Prices'!E10/'Monthly Prices'!E9-1,"") | F9: =IFERROR('Monthly Prices'!F10/'Monthly Prices'!F9-1,"") | G9: =IFERROR('Monthly Prices'!G10/'Monthly Prices'!G9-1,"") | H9: =IFERROR('Monthly Prices'!H10/'Monthly Prices'!H9-1,"") | I9: =IFERROR('Monthly Prices'!I10/'Monthly Prices'!I9-1,"") | ... K9: =IFERROR('Monthly Prices'!K10/'Monthly Prices'!K9-1,"") | L9: ='Risk-Free Rates'!C9 | M9: =MIN(B9-$L9,0) | N9: =MIN(C9-$L9,0) | O9: =MIN(D9-$L9,0) | P9: =MIN(E9-$L9,0) | Q9: =MIN(F9-$L9,0) | R9: =MIN(G9-$L9,0) | S9: =MIN(H9-$L9,0) | T9: =MIN(I9-$L9,0) | ... V9: =MIN(K9-$L9,0)
A10: 45351 | B10: =IFERROR('Monthly Prices'!B11/'Monthly Prices'!B10-1,"") | C10: =IFERROR('Monthly Prices'!C11/'Monthly Prices'!C10-1,"") | D10: =IFERROR('Monthly Prices'!D11/'Monthly Prices'!D10-1,"") | E10: =IFERROR('Monthly Prices'!E11/'Monthly Prices'!E10-1,"") | F10: =IFERROR('Monthly Prices'!F11/'Monthly Prices'!F10-1,"") | G10: =IFERROR('Monthly Prices'!G11/'Monthly Prices'!G10-1,"") | H10: =IFERROR('Monthly Prices'!H11/'Monthly Prices'!H10-1,"") | I10: =IFERROR('Monthly Prices'!I11/'Monthly Prices'!I10-1,"") | ... K10: =IFERROR('Monthly Prices'!K11/'Monthly Prices'!K10-1,"") | L10: ='Risk-Free Rates'!C10 | M10: =MIN(B10-$L10,0) | N10: =MIN(C10-$L10,0) | O10: =MIN(D10-$L10,0) | P10: =MIN(E10-$L10,0) | Q10: =MIN(F10-$L10,0) | R10: =MIN(G10-$L10,0) | S10: =MIN(H10-$L10,0) | T10: =MIN(I10-$L10,0) | ... V10: =MIN(K10-$L10,0)
A11: 45382 | B11: =IFERROR('Monthly Prices'!B12/'Monthly Prices'!B11-1,"") | C11: =IFERROR('Monthly Prices'!C12/'Monthly Prices'!C11-1,"") | D11: =IFERROR('Monthly Prices'!D12/'Monthly Prices'!D11-1,"") | E11: =IFERROR('Monthly Prices'!E12/'Monthly Prices'!E11-1,"") | F11: =IFERROR('Monthly Prices'!F12/'Monthly Prices'!F11-1,"") | G11: =IFERROR('Monthly Prices'!G12/'Monthly Prices'!G11-1,"") | H11: =IFERROR('Monthly Prices'!H12/'Monthly Prices'!H11-1,"") | I11: =IFERROR('Monthly Prices'!I12/'Monthly Prices'!I11-1,"") | ... K11: =IFERROR('Monthly Prices'!K12/'Monthly Prices'!K11-1,"") | L11: ='Risk-Free Rates'!C11 | M11: =MIN(B11-$L11,0) | N11: =MIN(C11-$L11,0) | O11: =MIN(D11-$L11,0) | P11: =MIN(E11-$L11,0) | Q11: =MIN(F11-$L11,0) | R11: =MIN(G11-$L11,0) | S11: =MIN(H11-$L11,0) | T11: =MIN(I11-$L11,0) | ... V11: =MIN(K11-$L11,0)
A12: 45412 | B12: =IFERROR('Monthly Prices'!B13/'Monthly Prices'!B12-1,"") | C12: =IFERROR('Monthly Prices'!C13/'Monthly Prices'!C12-1,"") | D12: =IFERROR('Monthly Prices'!D13/'Monthly Prices'!D12-1,"") | E12: =IFERROR('Monthly Prices'!E13/'Monthly Prices'!E12-1,"") | F12: =IFERROR('Monthly Prices'!F13/'Monthly Prices'!F12-1,"") | G12: =IFERROR('Monthly Prices'!G13/'Monthly Prices'!G12-1,"") | H12: =IFERROR('Monthly Prices'!H13/'Monthly Prices'!H12-1,"") | I12: =IFERROR('Monthly Prices'!I13/'Monthly Prices'!I12-1,"") | ... K12: =IFERROR('Monthly Prices'!K13/'Monthly Prices'!K12-1,"") | L12: ='Risk-Free Rates'!C12 | M12: =MIN(B12-$L12,0) | N12: =MIN(C12-$L12,0) | O12: =MIN(D12-$L12,0) | P12: =MIN(E12-$L12,0) | Q12: =MIN(F12-$L12,0) | R12: =MIN(G12-$L12,0) | S12: =MIN(H12-$L12,0) | T12: =MIN(I12-$L12,0) | ... V12: =MIN(K12-$L12,0)
A13: 45443 | B13: =IFERROR('Monthly Prices'!B14/'Monthly Prices'!B13-1,"") | C13: =IFERROR('Monthly Prices'!C14/'Monthly Prices'!C13-1,"") | D13: =IFERROR('Monthly Prices'!D14/'Monthly Prices'!D13-1,"") | E13: =IFERROR('Monthly Prices'!E14/'Monthly Prices'!E13-1,"") | F13: =IFERROR('Monthly Prices'!F14/'Monthly Prices'!F13-1,"") | G13: =IFERROR('Monthly Prices'!G14/'Monthly Prices'!G13-1,"") | H13: =IFERROR('Monthly Prices'!H14/'Monthly Prices'!H13-1,"") | I13: =IFERROR('Monthly Prices'!I14/'Monthly Prices'!I13-1,"") | ... K13: =IFERROR('Monthly Prices'!K14/'Monthly Prices'!K13-1,"") | L13: ='Risk-Free Rates'!C13 | M13: =MIN(B13-$L13,0) | N13: =MIN(C13-$L13,0) | O13: =MIN(D13-$L13,0) | P13: =MIN(E13-$L13,0) | Q13: =MIN(F13-$L13,0) | R13: =MIN(G13-$L13,0) | S13: =MIN(H13-$L13,0) | T13: =MIN(I13-$L13,0) | ... V13: =MIN(K13-$L13,0)
A14: 45473 | B14: =IFERROR('Monthly Prices'!B15/'Monthly Prices'!B14-1,"") | C14: =IFERROR('Monthly Prices'!C15/'Monthly Prices'!C14-1,"") | D14: =IFERROR('Monthly Prices'!D15/'Monthly Prices'!D14-1,"") | E14: =IFERROR('Monthly Prices'!E15/'Monthly Prices'!E14-1,"") | F14: =IFERROR('Monthly Prices'!F15/'Monthly Prices'!F14-1,"") | G14: =IFERROR('Monthly Prices'!G15/'Monthly Prices'!G14-1,"") | H14: =IFERROR('Monthly Prices'!H15/'Monthly Prices'!H14-1,"") | I14: =IFERROR('Monthly Prices'!I15/'Monthly Prices'!I14-1,"") | ... K14: =IFERROR('Monthly Prices'!K15/'Monthly Prices'!K14-1,"") | L14: ='Risk-Free Rates'!C14 | M14: =MIN(B14-$L14,0) | N14: =MIN(C14-$L14,0) | O14: =MIN(D14-$L14,0) | P14: =MIN(E14-$L14,0) | Q14: =MIN(F14-$L14,0) | R14: =MIN(G14-$L14,0) | S14: =MIN(H14-$L14,0) | T14: =MIN(I14-$L14,0) | ... V14: =MIN(K14-$L14,0)
A15: 45504 | B15: =IFERROR('Monthly Prices'!B16/'Monthly Prices'!B15-1,"") | C15: =IFERROR('Monthly Prices'!C16/'Monthly Prices'!C15-1,"") | D15: =IFERROR('Monthly Prices'!D16/'Monthly Prices'!D15-1,"") | E15: =IFERROR('Monthly Prices'!E16/'Monthly Prices'!E15-1,"") | F15: =IFERROR('Monthly Prices'!F16/'Monthly Prices'!F15-1,"") | G15: =IFERROR('Monthly Prices'!G16/'Monthly Prices'!G15-1,"") | H15: =IFERROR('Monthly Prices'!H16/'Monthly Prices'!H15-1,"") | I15: =IFERROR('Monthly Prices'!I16/'Monthly Prices'!I15-1,"") | ... K15: =IFERROR('Monthly Prices'!K16/'Monthly Prices'!K15-1,"") | L15: ='Risk-Free Rates'!C15 | M15: =MIN(B15-$L15,0) | N15: =MIN(C15-$L15,0) | O15: =MIN(D15-$L15,0) | P15: =MIN(E15-$L15,0) | Q15: =MIN(F15-$L15,0) | R15: =MIN(G15-$L15,0) | S15: =MIN(H15-$L15,0) | T15: =MIN(I15-$L15,0) | ... V15: =MIN(K15-$L15,0)
A16: 45535 | B16: =IFERROR('Monthly Prices'!B17/'Monthly Prices'!B16-1,"") | C16: =IFERROR('Monthly Prices'!C17/'Monthly Prices'!C16-1,"") | D16: =IFERROR('Monthly Prices'!D17/'Monthly Prices'!D16-1,"") | E16: =IFERROR('Monthly Prices'!E17/'Monthly Prices'!E16-1,"") | F16: =IFERROR('Monthly Prices'!F17/'Monthly Prices'!F16-1,"") | G16: =IFERROR('Monthly Prices'!G17/'Monthly Prices'!G16-1,"") | H16: =IFERROR('Monthly Prices'!H17/'Monthly Prices'!H16-1,"") | I16: =IFERROR('Monthly Prices'!I17/'Monthly Prices'!I16-1,"") | ... K16: =IFERROR('Monthly Prices'!K17/'Monthly Prices'!K16-1,"") | L16: ='Risk-Free Rates'!C16 | M16: =MIN(B16-$L16,0) | N16: =MIN(C16-$L16,0) | O16: =MIN(D16-$L16,0) | P16: =MIN(E16-$L16,0) | Q16: =MIN(F16-$L16,0) | R16: =MIN(G16-$L16,0) | S16: =MIN(H16-$L16,0) | T16: =MIN(I16-$L16,0) | ... V16: =MIN(K16-$L16,0)
... A40: 46265 | B40: =IFERROR('Monthly Prices'!B41/'Monthly Prices'!B40-1,"") | C40: =IFERROR('Monthly Prices'!C41/'Monthly Prices'!C40-1,"") | D40: =IFERROR('Monthly Prices'!D41/'Monthly Prices'!D40-1,"") | E40: =IFERROR('Monthly Prices'!E41/'Monthly Prices'!E40-1,"") | F40: =IFERROR('Monthly Prices'!F41/'Monthly Prices'!F40-1,"") | G40: =IFERROR('Monthly Prices'!G41/'Monthly Prices'!G40-1,"") | H40: =IFERROR('Monthly Prices'!H41/'Monthly Prices'!H40-1,"") | I40: =IFERROR('Monthly Prices'!I41/'Monthly Prices'!I40-1,"") | ... K40: =IFERROR('Monthly Prices'!K41/'Monthly Prices'!K40-1,"") | L40: ='Risk-Free Rates'!C40 | M40: =MIN(B40-$L40,0) | N40: =MIN(C40-$L40,0) | O40: =MIN(D40-$L40,0) | P40: =MIN(E40-$L40,0) | Q40: =MIN(F40-$L40,0) | R40: =MIN(G40-$L40,0) | S40: =MIN(H40-$L40,0) | T40: =MIN(I40-$L40,0) | ... V40: =MIN(K40-$L40,0)

Sheet Risk-Free Rates
A1: Risk-Free Rate Series
A2: Return-month alignment plus the last available business-day 3-month U.S. Treasury constant-maturity yield (FRED DGS3MO).
A4: Return Month | B4: DGS3MO Annual Yield | C4: Monthly Equivalent | D4: Source URL | E4: FRED Observation Date
A5: 45199 | B5: 0.0555 | C5: =(1+B5)^(1/12)-1 | D5: https://fred.stlouisfed.org/series/DGS3MO | E5: 45198
A6: 45230 | B6: 0.0559 | C6: =(1+B6)^(1/12)-1 | D6: https://fred.stlouisfed.org/series/DGS3MO | E6: 45230
A7: 45260 | B7: 0.0545 | C7: =(1+B7)^(1/12)-1 | D7: https://fred.stlouisfed.org/series/DGS3MO | E7: 45260
A8: 45291 | B8: 0.054 | C8: =(1+B8)^(1/12)-1 | D8: https://fred.stlouisfed.org/series/DGS3MO | E8: 45289
A9: 45322 | B9: 0.0542 | C9: =(1+B9)^(1/12)-1 | D9: https://fred.stlouisfed.org/series/DGS3MO | E9: 45322
A10: 45351 | B10: 0.0545 | C10: =(1+B10)^(1/12)-1 | D10: https://fred.stlouisfed.org/series/DGS3MO | E10: 45351
A11: 45382 | B11: 0.0546 | C11: =(1+B11)^(1/12)-1 | D11: https://fred.stlouisfed.org/series/DGS3MO | E11: 45379
A12: 45412 | B12: 0.0546 | C12: =(1+B12)^(1/12)-1 | D12: https://fred.stlouisfed.org/series/DGS3MO | E12: 45412
A13: 45443 | B13: 0.0546 | C13: =(1+B13)^(1/12)-1 | D13: https://fred.stlouisfed.org/series/DGS3MO | E13: 45443
A14: 45473 | B14: 0.0548 | C14: =(1+B14)^(1/12)-1 | D14: https://fred.stlouisfed.org/series/DGS3MO | E14: 45471
A15: 45504 | B15: 0.0541 | C15: =(1+B15)^(1/12)-1 | D15: https://fred.stlouisfed.org/series/DGS3MO | E15: 45504
A16: 45535 | B16: 0.0521 | C16: =(1+B16)^(1/12)-1 | D16: https://fred.stlouisfed.org/series/DGS3MO | E16: 45534
... A40: 46265 | B40: 0.0391 | C40: =(1+B40)^(1/12)-1 | D40: https://fred.stlouisfed.org/series/DGS3MO | E40: 46265

Sheet Drawdown Calc
A1: Month-End Drawdown Calculations
A2: Drawdowns are measured from month-end adjusted prices, so intramonth peak-to-trough losses can be larger.
A4: Date | B4: SPY | C4: QQQ | D4: IWM | E4: EFA | F4: EEM | G4: AGG | H4: LQD | I4: HYG | J4: GLD | K4: VNQ
A5: 45169 | B5: ='Monthly Prices'!B5/MAX('Monthly Prices'!$B$5:'Monthly Prices'!B5)-1 | C5: ='Monthly Prices'!C5/MAX('Monthly Prices'!$C$5:'Monthly Prices'!C5)-1 | D5: ='Monthly Prices'!D5/MAX('Monthly Prices'!$D$5:'Monthly Prices'!D5)-1 | E5: ='Monthly Prices'!E5/MAX('Monthly Prices'!$E$5:'Monthly Prices'!E5)-1 | F5: ='Monthly Prices'!F5/MAX('Monthly Prices'!$F$5:'Monthly Prices'!F5)-1 | G5: ='Monthly Prices'!G5/MAX('Monthly Prices'!$G$5:'Monthly Prices'!G5)-1 | H5: ='Monthly Prices'!H5/MAX('Monthly Prices'!$H$5:'Monthly Prices'!H5)-1 | I5: ='Monthly Prices'!I5/MAX('Monthly Prices'!$I$5:'Monthly Prices'!I5)-1 | J5: ='Monthly Prices'!J5/MAX('Monthly Prices'!$J$5:'Monthly Prices'!J5)-1 | K5: ='Monthly Prices'!K5/MAX('Monthly Prices'!$K$5:'Monthly Prices'!K5)-1
A6: 45199 | B6: ='Monthly Prices'!B6/MAX('Monthly Prices'!$B$5:'Monthly Prices'!B6)-1 | C6: ='Monthly Prices'!C6/MAX('Monthly Prices'!$C$5:'Monthly Prices'!C6)-1 | D6: ='Monthly Prices'!D6/MAX('Monthly Prices'!$D$5:'Monthly Prices'!D6)-1 | E6: ='Monthly Prices'!E6/MAX('Monthly Prices'!$E$5:'Monthly Prices'!E6)-1 | F6: ='Monthly Prices'!F6/MAX('Monthly Prices'!$F$5:'Monthly Prices'!F6)-1 | G6: ='Monthly Prices'!G6/MAX('Monthly Prices'!$G$5:'Monthly Prices'!G6)-1 | H6: ='Monthly Prices'!H6/MAX('Monthly Prices'!$H$5:'Monthly Prices'!H6)-1 | I6: ='Monthly Prices'!I6/MAX('Monthly Prices'!$I$5:'Monthly Prices'!I6)-1 | J6: ='Monthly Prices'!J6/MAX('Monthly Prices'!$J$5:'Monthly Prices'!J6)-1 | K6: ='Monthly Prices'!K6/MAX('Monthly Prices'!$K$5:'Monthly Prices'!K6)-1
A7: 45230 | B7: ='Monthly Prices'!B7/MAX('Monthly Prices'!$B$5:'Monthly Prices'!B7)-1 | C7: ='Monthly Prices'!C7/MAX('Monthly Prices'!$C$5:'Monthly Prices'!C7)-1 | D7: ='Monthly Prices'!D7/MAX('Monthly Prices'!$D$5:'Monthly Prices'!D7)-1 | E7: ='Monthly Prices'!E7/MAX('Monthly Prices'!$E$5:'Monthly Prices'!E7)-1 | F7: ='Monthly Prices'!F7/MAX('Monthly Prices'!$F$5:'Monthly Prices'!F7)-1 | G7: ='Monthly Prices'!G7/MAX('Monthly Prices'!$G$5:'Monthly Prices'!G7)-1 | H7: ='Monthly Prices'!H7/MAX('Monthly Prices'!$H$5:'Monthly Prices'!H7)-1 | I7: ='Monthly Prices'!I7/MAX('Monthly Prices'!$I$5:'Monthly Prices'!I7)-1 | J7: ='Monthly Prices'!J7/MAX('Monthly Prices'!$J$5:'Monthly Prices'!J7)-1 | K7: ='Monthly Prices'!K7/MAX('Monthly Prices'!$K$5:'Monthly Prices'!K7)-1
A8: 45260 | B8: ='Monthly Prices'!B8/MAX('Monthly Prices'!$B$5:'Monthly Prices'!B8)-1 | C8: ='Monthly Prices'!C8/MAX('Monthly Prices'!$C$5:'Monthly Prices'!C8)-1 | D8: ='Monthly Prices'!D8/MAX('Monthly Prices'!$D$5:'Monthly Prices'!D8)-1 | E8: ='Monthly Prices'!E8/MAX('Monthly Prices'!$E$5:'Monthly Prices'!E8)-1 | F8: ='Monthly Prices'!F8/MAX('Monthly Prices'!$F$5:'Monthly Prices'!F8)-1 | G8: ='Monthly Prices'!G8/MAX('Monthly Prices'!$G$5:'Monthly Prices'!G8)-1 | H8: ='Monthly Prices'!H8/MAX('Monthly Prices'!$H$5:'Monthly Prices'!H8)-1 | I8: ='Monthly Prices'!I8/MAX('Monthly Prices'!$I$5:'Monthly Prices'!I8)-1 | J8: ='Monthly Prices'!J8/MAX('Monthly Prices'!$J$5:'Monthly Prices'!J8)-1 | K8: ='Monthly Prices'!K8/MAX('Monthly Prices'!$K$5:'Monthly Prices'!K8)-1
A9: 45291 | B9: ='Monthly Prices'!B9/MAX('Monthly Prices'!$B$5:'Monthly Prices'!B9)-1 | C9: ='Monthly Prices'!C9/MAX('Monthly Prices'!$C$5:'Monthly Prices'!C9)-1 | D9: ='Monthly Prices'!D9/MAX('Monthly Prices'!$D$5:'Monthly Prices'!D9)-1 | E9: ='Monthly Prices'!E9/MAX('Monthly Prices'!$E$5:'Monthly Prices'!E9)-1 | F9: ='Monthly Prices'!F9/MAX('Monthly Prices'!$F$5:'Monthly Prices'!F9)-1 | G9: ='Monthly Prices'!G9/MAX('Monthly Prices'!$G$5:'Monthly Prices'!G9)-1 | H9: ='Monthly Prices'!H9/MAX('Monthly Prices'!$H$5:'Monthly Prices'!H9)-1 | I9: ='Monthly Prices'!I9/MAX('Monthly Prices'!$I$5:'Monthly Prices'!I9)-1 | J9: ='Monthly Prices'!J9/MAX('Monthly Prices'!$J$5:'Monthly Prices'!J9)-1 | K9: ='Monthly Prices'!K9/MAX('Monthly Prices'!$K$5:'Monthly Prices'!K9)-1
A10: 45322 | B10: ='Monthly Prices'!B10/MAX('Monthly Prices'!$B$5:'Monthly Prices'!B10)-1 | C10: ='Monthly Prices'!C10/MAX('Monthly Prices'!$C$5:'Monthly Prices'!C10)-1 | D10: ='Monthly Prices'!D10/MAX('Monthly Prices'!$D$5:'Monthly Prices'!D10)-1 | E10: ='Monthly Prices'!E10/MAX('Monthly Prices'!$E$5:'Monthly Prices'!E10)-1 | F10: ='Monthly Prices'!F10/MAX('Monthly Prices'!$F$5:'Monthly Prices'!F10)-1 | G10: ='Monthly Prices'!G10/MAX('Monthly Prices'!$G$5:'Monthly Prices'!G10)-1 | H10: ='Monthly Prices'!H10/MAX('Monthly Prices'!$H$5:'Monthly Prices'!H10)-1 | I10: ='Monthly Prices'!I10/MAX('Monthly Prices'!$I$5:'Monthly Prices'!I10)-1 | J10: ='Monthly Prices'!J10/MAX('Monthly Prices'!$J$5:'Monthly Prices'!J10)-1 | K10: ='Monthly Prices'!K10/MAX('Monthly Prices'!$K$5:'Monthly Prices'!K10)-1
A11: 45351 | B11: ='Monthly Prices'!B11/MAX('Monthly Prices'!$B$5:'Monthly Prices'!B11)-1 | C11: ='Monthly Prices'!C11/MAX('Monthly Prices'!$C$5:'Monthly Prices'!C11)-1 | D11: ='Monthly Prices'!D11/MAX('Monthly Prices'!$D$5:'Monthly Prices'!D11)-1 | E11: ='Monthly Prices'!E11/MAX('Monthly Prices'!$E$5:'Monthly Prices'!E11)-1 | F11: ='Monthly Prices'!F11/MAX('Monthly Prices'!$F$5:'Monthly Prices'!F11)-1 | G11: ='Monthly Prices'!G11/MAX('Monthly Prices'!$G$5:'Monthly Prices'!G11)-1 | H11: ='Monthly Prices'!H11/MAX('Monthly Prices'!$H$5:'Monthly Prices'!H11)-1 | I11: ='Monthly Prices'!I11/MAX('Monthly Prices'!$I$5:'Monthly Prices'!I11)-1 | J11: ='Monthly Prices'!J11/MAX('Monthly Prices'!$J$5:'Monthly Prices'!J11)-1 | K11: ='Monthly Prices'!K11/MAX('Monthly Prices'!$K$5:'Monthly Prices'!K11)-1
A12: 45382 | B12: ='Monthly Prices'!B12/MAX('Monthly Prices'!$B$5:'Monthly Prices'!B12)-1 | C12: ='Monthly Prices'!C12/MAX('Monthly Prices'!$C$5:'Monthly Prices'!C12)-1 | D12: ='Monthly Prices'!D12/MAX('Monthly Prices'!$D$5:'Monthly Prices'!D12)-1 | E12: ='Monthly Prices'!E12/MAX('Monthly Prices'!$E$5:'Monthly Prices'!E12)-1 | F12: ='Monthly Prices'!F12/MAX('Monthly Prices'!$F$5:'Monthly Prices'!F12)-1 | G12: ='Monthly Prices'!G12/MAX('Monthly Prices'!$G$5:'Monthly Prices'!G12)-1 | H12: ='Monthly Prices'!H12/MAX('Monthly Prices'!$H$5:'Monthly Prices'!H12)-1 | I12: ='Monthly Prices'!I12/MAX('Monthly Prices'!$I$5:'Monthly Prices'!I12)-1 | J12: ='Monthly Prices'!J12/MAX('Monthly Prices'!$J$5:'Monthly Prices'!J12)-1 | K12: ='Monthly Prices'!K12/MAX('Monthly Prices'!$K$5:'Monthly Prices'!K12)-1
A13: 45412 | B13: ='Monthly Prices'!B13/MAX('Monthly Prices'!$B$5:'Monthly Prices'!B13)-1 | C13: ='Monthly Prices'!C13/MAX('Monthly Prices'!$C$5:'Monthly Prices'!C13)-1 | D13: ='Monthly Prices'!D13/MAX('Monthly Prices'!$D$5:'Monthly Prices'!D13)-1 | E13: ='Monthly Prices'!E13/MAX('Monthly Prices'!$E$5:'Monthly Prices'!E13)-1 | F13: ='Monthly Prices'!F13/MAX('Monthly Prices'!$F$5:'Monthly Prices'!F13)-1 | G13: ='Monthly Prices'!G13/MAX('Monthly Prices'!$G$5:'Monthly Prices'!G13)-1 | H13: ='Monthly Prices'!H13/MAX('Monthly Prices'!$H$5:'Monthly Prices'!H13)-1 | I13: ='Monthly Prices'!I13/MAX('Monthly Prices'!$I$5:'Monthly Prices'!I13)-1 | J13: ='Monthly Prices'!J13/MAX('Monthly Prices'!$J$5:'Monthly Prices'!J13)-1 | K13: ='Monthly Prices'!K13/MAX('Monthly Prices'!$K$5:'Monthly Prices'!K13)-1
A14: 45443 | B14: ='Monthly Prices'!B14/MAX('Monthly Prices'!$B$5:'Monthly Prices'!B14)-1 | C14: ='Monthly Prices'!C14/MAX('Monthly Prices'!$C$5:'Monthly Prices'!C14)-1 | D14: ='Monthly Prices'!D14/MAX('Monthly Prices'!$D$5:'Monthly Prices'!D14)-1 | E14: ='Monthly Prices'!E14/MAX('Monthly Prices'!$E$5:'Monthly Prices'!E14)-1 | F14: ='Monthly Prices'!F14/MAX('Monthly Prices'!$F$5:'Monthly Prices'!F14)-1 | G14: ='Monthly Prices'!G14/MAX('Monthly Prices'!$G$5:'Monthly Prices'!G14)-1 | H14: ='Monthly Prices'!H14/MAX('Monthly Prices'!$H$5:'Monthly Prices'!H14)-1 | I14: ='Monthly Prices'!I14/MAX('Monthly Prices'!$I$5:'Monthly Prices'!I14)-1 | J14: ='Monthly Prices'!J14/MAX('Monthly Prices'!$J$5:'Monthly Prices'!J14)-1 | K14: ='Monthly Prices'!K14/MAX('Monthly Prices'!$K$5:'Monthly Prices'!K14)-1
A15: 45473 | B15: ='Monthly Prices'!B15/MAX('Monthly Prices'!$B$5:'Monthly Prices'!B15)-1 | C15: ='Monthly Prices'!C15/MAX('Monthly Prices'!$C$5:'Monthly Prices'!C15)-1 | D15: ='Monthly Prices'!D15/MAX('Monthly Prices'!$D$5:'Monthly Prices'!D15)-1 | E15: ='Monthly Prices'!E15/MAX('Monthly Prices'!$E$5:'Monthly Prices'!E15)-1 | F15: ='Monthly Prices'!F15/MAX('Monthly Prices'!$F$5:'Monthly Prices'!F15)-1 | G15: ='Monthly Prices'!G15/MAX('Monthly Prices'!$G$5:'Monthly Prices'!G15)-1 | H15: ='Monthly Prices'!H15/MAX('Monthly Prices'!$H$5:'Monthly Prices'!H15)-1 | I15: ='Monthly Prices'!I15/MAX('Monthly Prices'!$I$5:'Monthly Prices'!I15)-1 | J15: ='Monthly Prices'!J15/MAX('Monthly Prices'!$J$5:'Monthly Prices'!J15)-1 | K15: ='Monthly Prices'!K15/MAX('Monthly Prices'!$K$5:'Monthly Prices'!K15)-1
A16: 45504 | B16: ='Monthly Prices'!B16/MAX('Monthly Prices'!$B$5:'Monthly Prices'!B16)-1 | C16: ='Monthly Prices'!C16/MAX('Monthly Prices'!$C$5:'Monthly Prices'!C16)-1 | D16: ='Monthly Prices'!D16/MAX('Monthly Prices'!$D$5:'Monthly Prices'!D16)-1 | E16: ='Monthly Prices'!E16/MAX('Monthly Prices'!$E$5:'Monthly Prices'!E16)-1 | F16: ='Monthly Prices'!F16/MAX('Monthly Prices'!$F$5:'Monthly Prices'!F16)-1 | G16: ='Monthly Prices'!G16/MAX('Monthly Prices'!$G$5:'Monthly Prices'!G16)-1 | H16: ='Monthly Prices'!H16/MAX('Monthly Prices'!$H$5:'Monthly Prices'!H16)-1 | I16: ='Monthly Prices'!I16/MAX('Monthly Prices'!$I$5:'Monthly Prices'!I16)-1 | J16: ='Monthly Prices'!J16/MAX('Monthly Prices'!$J$5:'Monthly Prices'!J16)-1 | K16: ='Monthly Prices'!K16/MAX('Monthly Prices'!$K$5:'Monthly Prices'!K16)-1
... A41: 46265 | B41: ='Monthly Prices'!B41/MAX('Monthly Prices'!$B$5:'Monthly Prices'!B41)-1 | C41: ='Monthly Prices'!C41/MAX('Monthly Prices'!$C$5:'Monthly Prices'!C41)-1 | D41: ='Monthly Prices'!D41/MAX('Monthly Prices'!$D$5:'Monthly Prices'!D41)-1 | E41: ='Monthly Prices'!E41/MAX('Monthly Prices'!$E$5:'Monthly Prices'!E41)-1 | F41: ='Monthly Prices'!F41/MAX('Monthly Prices'!$F$5:'Monthly Prices'!F41)-1 | G41: ='Monthly Prices'!G41/MAX('Monthly Prices'!$G$5:'Monthly Prices'!G41)-1 | H41: ='Monthly Prices'!H41/MAX('Monthly Prices'!$H$5:'Monthly Prices'!H41)-1 | I41: ='Monthly Prices'!I41/MAX('Monthly Prices'!$I$5:'Monthly Prices'!I41)-1 | J41: ='Monthly Prices'!J41/MAX('Monthly Prices'!$J$5:'Monthly Prices'!J41)-1 | K41: ='Monthly Prices'!K41/MAX('Monthly Prices'!$K$5:'Monthly Prices'!K41)-1

Sheet Correlation Matrix
A1: Monthly Return Correlation Matrix | Aug 2023–Aug 2026
A2: Formula-driven from the Monthly Returns sheet.
A4: Ticker | B4: SPY | C4: QQQ | D4: IWM | E4: EFA | F4: EEM | G4: AGG | H4: LQD | I4: HYG | J4: GLD | K4: VNQ
A5: SPY | B5: =CORREL('Monthly Returns'!B5:B40,'Monthly Returns'!B5:B40) | C5: =CORREL('Monthly Returns'!B5:B40,'Monthly Returns'!C5:C40) | D5: =CORREL('Monthly Returns'!B5:B40,'Monthly Returns'!D5:D40) | E5: =CORREL('Monthly Returns'!B5:B40,'Monthly Returns'!E5:E40) | F5: =CORREL('Monthly Returns'!B5:B40,'Monthly Returns'!F5:F40) | G5: =CORREL('Monthly Returns'!B5:B40,'Monthly Returns'!G5:G40) | H5: =CORREL('Monthly Returns'!B5:B40,'Monthly Returns'!H5:H40) | I5: =CORREL('Monthly Returns'!B5:B40,'Monthly Returns'!I5:I40) | J5: =CORREL('Monthly Returns'!B5:B40,'Monthly Returns'!J5:J40) | K5: =CORREL('Monthly Returns'!B5:B40,'Monthly Returns'!K5:K40)
A6: QQQ | B6: =CORREL('Monthly Returns'!C5:C40,'Monthly Returns'!B5:B40) | C6: =CORREL('Monthly Returns'!C5:C40,'Monthly Returns'!C5:C40) | D6: =CORREL('Monthly Returns'!C5:C40,'Monthly Returns'!D5:D40) | E6: =CORREL('Monthly Returns'!C5:C40,'Monthly Returns'!E5:E40) | F6: =CORREL('Monthly Returns'!C5:C40,'Monthly Returns'!F5:F40) | G6: =CORREL('Monthly Returns'!C5:C40,'Monthly Returns'!G5:G40) | H6: =CORREL('Monthly Returns'!C5:C40,'Monthly Returns'!H5:H40) | I6: =CORREL('Monthly Returns'!C5:C40,'Monthly Returns'!I5:I40) | J6: =CORREL('Monthly Returns'!C5:C40,'Monthly Returns'!J5:J40) | K6: =CORREL('Monthly Returns'!C5:C40,'Monthly Returns'!K5:K40)
A7: IWM | B7: =CORREL('Monthly Returns'!D5:D40,'Monthly Returns'!B5:B40) | C7: =CORREL('Monthly Returns'!D5:D40,'Monthly Returns'!C5:C40) | D7: =CORREL('Monthly Returns'!D5:D40,'Monthly Returns'!D5:D40) | E7: =CORREL('Monthly Returns'!D5:D40,'Monthly Returns'!E5:E40) | F7: =CORREL('Monthly Returns'!D5:D40,'Monthly Returns'!F5:F40) | G7: =CORREL('Monthly Returns'!D5:D40,'Monthly Returns'!G5:G40) | H7: =CORREL('Monthly Returns'!D5:D40,'Monthly Returns'!H5:H40) | I7: =CORREL('Monthly Returns'!D5:D40,'Monthly Returns'!I5:I40) | J7: =CORREL('Monthly Returns'!D5:D40,'Monthly Returns'!J5:J40) | K7: =CORREL('Monthly Returns'!D5:D40,'Monthly Returns'!K5:K40)
A8: EFA | B8: =CORREL('Monthly Returns'!E5:E40,'Monthly Returns'!B5:B40) | C8: =CORREL('Monthly Returns'!E5:E40,'Monthly Returns'!C5:C40) | D8: =CORREL('Monthly Returns'!E5:E40,'Monthly Returns'!D5:D40) | E8: =CORREL('Monthly Returns'!E5:E40,'Monthly Returns'!E5:E40) | F8: =CORREL('Monthly Returns'!E5:E40,'Monthly Returns'!F5:F40) | G8: =CORREL('Monthly Returns'!E5:E40,'Monthly Returns'!G5:G40) | H8: =CORREL('Monthly Returns'!E5:E40,'Monthly Returns'!H5:H40) | I8: =CORREL('Monthly Returns'!E5:E40,'Monthly Returns'!I5:I40) | J8: =CORREL('Monthly Returns'!E5:E40,'Monthly Returns'!J5:J40) | K8: =CORREL('Monthly Returns'!E5:E40,'Monthly Returns'!K5:K40)
A9: EEM | B9: =CORREL('Monthly Returns'!F5:F40,'Monthly Returns'!B5:B40) | C9: =CORREL('Monthly Returns'!F5:F40,'Monthly Returns'!C5:C40) | D9: =CORREL('Monthly Returns'!F5:F40,'Monthly Returns'!D5:D40) | E9: =CORREL('Monthly Returns'!F5:F40,'Monthly Returns'!E5:E40) | F9: =CORREL('Monthly Returns'!F5:F40,'Monthly Returns'!F5:F40) | G9: =CORREL('Monthly Returns'!F5:F40,'Monthly Returns'!G5:G40) | H9: =CORREL('Monthly Returns'!F5:F40,'Monthly Returns'!H5:H40) | I9: =CORREL('Monthly Returns'!F5:F40,'Monthly Returns'!I5:I40) | J9: =CORREL('Monthly Returns'!F5:F40,'Monthly Returns'!J5:J40) | K9: =CORREL('Monthly Returns'!F5:F40,'Monthly Returns'!K5:K40)
A10: AGG | B10: =CORREL('Monthly Returns'!G5:G40,'Monthly Returns'!B5:B40) | C10: =CORREL('Monthly Returns'!G5:G40,'Monthly Returns'!C5:C40) | D10: =CORREL('Monthly Returns'!G5:G40,'Monthly Returns'!D5:D40) | E10: =CORREL('Monthly Returns'!G5:G40,'Monthly Returns'!E5:E40) | F10: =CORREL('Monthly Returns'!G5:G40,'Monthly Returns'!F5:F40) | G10: =CORREL('Monthly Returns'!G5:G40,'Monthly Returns'!G5:G40) | H10: =CORREL('Monthly Returns'!G5:G40,'Monthly Returns'!H5:H40) | I10: =CORREL('Monthly Returns'!G5:G40,'Monthly Returns'!I5:I40) | J10: =CORREL('Monthly Returns'!G5:G40,'Monthly Returns'!J5:J40) | K10: =CORREL('Monthly Returns'!G5:G40,'Monthly Returns'!K5:K40)
A11: LQD | B11: =CORREL('Monthly Returns'!H5:H40,'Monthly Returns'!B5:B40) | C11: =CORREL('Monthly Returns'!H5:H40,'Monthly Returns'!C5:C40) | D11: =CORREL('Monthly Returns'!H5:H40,'Monthly Returns'!D5:D40) | E11: =CORREL('Monthly Returns'!H5:H40,'Monthly Returns'!E5:E40) | F11: =CORREL('Monthly Returns'!H5:H40,'Monthly Returns'!F5:F40) | G11: =CORREL('Monthly Returns'!H5:H40,'Monthly Returns'!G5:G40) | H11: =CORREL('Monthly Returns'!H5:H40,'Monthly Returns'!H5:H40) | I11: =CORREL('Monthly Returns'!H5:H40,'Monthly Returns'!I5:I40) | J11: =CORREL('Monthly Returns'!H5:H40,'Monthly Returns'!J5:J40) | K11: =CORREL('Monthly Returns'!H5:H40,'Monthly Returns'!K5:K40)
A12: HYG | B12: =CORREL('Monthly Returns'!I5:I40,'Monthly Returns'!B5:B40) | C12: =CORREL('Monthly Returns'!I5:I40,'Monthly Returns'!C5:C40) | D12: =CORREL('Monthly Returns'!I5:I40,'Monthly Returns'!D5:D40) | E12: =CORREL('Monthly Returns'!I5:I40,'Monthly Returns'!E5:E40) | F12: =CORREL('Monthly Returns'!I5:I40,'Monthly Returns'!F5:F40) | G12: =CORREL('Monthly Returns'!I5:I40,'Monthly Returns'!G5:G40) | H12: =CORREL('Monthly Returns'!I5:I40,'Monthly Returns'!H5:H40) | I12: =CORREL('Monthly Returns'!I5:I40,'Monthly Returns'!I5:I40) | J12: =CORREL('Monthly Returns'!I5:I40,'Monthly Returns'!J5:J40) | K12: =CORREL('Monthly Returns'!I5:I40,'Monthly Returns'!K5:K40)
A13: GLD | B13: =CORREL('Monthly Returns'!J5:J40,'Monthly Returns'!B5:B40) | C13: =CORREL('Monthly Returns'!J5:J40,'Monthly Returns'!C5:C40) | D13: =CORREL('Monthly Returns'!J5:J40,'Monthly Returns'!D5:D40) | E13: =CORREL('Monthly Returns'!J5:J40,'Monthly Returns'!E5:E40) | F13: =CORREL('Monthly Returns'!J5:J40,'Monthly Returns'!F5:F40) | G13: =CORREL('Monthly Returns'!J5:J40,'Monthly Returns'!G5:G40) | H13: =CORREL('Monthly Returns'!J5:J40,'Monthly Returns'!H5:H40) | I13: =CORREL('Monthly Returns'!J5:J40,'Monthly Returns'!I5:I40) | J13: =CORREL('Monthly Returns'!J5:J40,'Monthly Returns'!J5:J40) | K13: =CORREL('Monthly Returns'!J5:J40,'Monthly Returns'!K5:K40)
A14: VNQ | B14: =CORREL('Monthly Returns'!K5:K40,'Monthly Returns'!B5:B40) | C14: =CORREL('Monthly Returns'!K5:K40,'Monthly Returns'!C5:C40) | D14: =CORREL('Monthly Returns'!K5:K40,'Monthly Returns'!D5:D40) | E14: =CORREL('Monthly Returns'!K5:K40,'Monthly Returns'!E5:E40) | F14: =CORREL('Monthly Returns'!K5:K40,'Monthly Returns'!F5:F40) | G14: =CORREL('Monthly Returns'!K5:K40,'Monthly Returns'!G5:G40) | H14: =CORREL('Monthly Returns'!K5:K40,'Monthly Returns'!H5:H40) | I14: =CORREL('Monthly Returns'!K5:K40,'Monthly Returns'!I5:I40) | J14: =CORREL('Monthly Returns'!K5:K40,'Monthly Returns'!J5:J40) | K14: =CORREL('Monthly Returns'!K5:K40,'Monthly Returns'!K5:K40)

Sheet Strategy Case
A1: Product Development Case
A2: Translate competitor economics and quantitative analysis into a business recommendation.
A4: Decision Question
A6: Should an asset manager enter the broad emerging-markets ETF category with another low-cost passive product, or pursue a differentiated active/systematic proposition?
A10: Evidence
A12: Price compression | B12: Four of five selected core peers charge 0.06%–0.09%; competing purely on price would be difficult.
A13: Scale concentration | B13: IEMG and VWO dominate the selected peer set by AUM, suggesting incumbent scale and distribution matter.
A14: Liquidity premium | B14: EEM remains large despite a 0.72% expense ratio, illustrating that liquidity/trading utility can support a premium proposition.
A15: MSIM platform fit | B15: MSIM publicly emphasizes differentiated active/systematic ETF solutions and outcomes such as downside-risk management and capital appreciation.
A16: Quantitative EM evidence | B16: EEM generated a 22.5% CAGR over Aug 2023–Aug 2026 with 15.4% annualized monthly volatility, a -9.3% month-end max drawdown, and 0.79 beta to SPY.
A17: Cross-asset risk lens | B17: Gold provided near-zero correlation with SPY in this window, while high-yield credit remained strongly equity-sensitive—reinforcing the importance of explicit risk controls and diversification thinking.
A18: Illustrative Concept
A20: Working name | B20: MSIM Emerging Markets Quality & Risk ETF (hypothetical)
A21: Investment idea | B21: Systematic selection emphasizing profitability, balance-sheet strength, and earnings quality within a diversified EM universe.
A22: Risk architecture | B22: Country and sector concentration limits, liquidity screens, and explicit portfolio-volatility / drawdown monitoring.
A23: Client outcome | B23: Broad EM participation with a more disciplined risk profile than undifferentiated cap-weighted beta.
A24: Target channel | B24: Wealth platforms, RIAs, model portfolios, and institutional allocators seeking EM exposure with a differentiated process.
A25: Economics | B25: Illustrative mid-range fee rather than fee-floor positioning; exact pricing would require a full market scan and distribution economics.
A28: Risks / Questions to Test Before Launch
A30: • Is the differentiated outcome clear enough to overcome incumbent scale and distribution advantages?
A31: • How much active risk / tracking error is acceptable for model-portfolio and wealth buyers?
A32: • What fee level balances product economics with competitive positioning?
A33: • Can the strategy maintain sufficient liquidity and capacity across emerging-market securities?
A34: • Would an ETF wrapper create tax, trading, or transparency advantages relative to existing vehicles?

Sheet Sources
A1: Sources & Data Notes
A2: Public-source reference log for the project. Refresh dates and metrics before publishing or interviewing.
A4: Source | B4: Used For | C4: Access / Data Date | D4: URL | E4: Notes
A5: Morgan Stanley job posting | B5: Role requirements and team responsibilities | C5: Crawled 2026-09-19 | D5: https://morganstanley.tal.net/vx/candidate/so/pm/1/pl/1/opp/20910 | E5: Strategic Functions: IM Strategy, Product Development, ETFs, Office of COO, Global Risk & Analysis.
A6: Morgan Stanley ETF campaign | B6: MSIM ETF positioning | C6: Crawled Sep 2026 | D6: https://www.morganstanley.com/im/en-us/individual-investor/campaigns/our-etfs.html | E6: MSIM highlights active/systematic differentiated solutions and investor outcomes.
A7: Morgan Stanley ETP launch | B7: MSIM ETF/ETP platform scale | C7: 2026-07-28 | D7: https://www.morganstanley.com/im/en-us/capital-seeker/about-us/news-and-insights/press-release/msim-expands-etp-offerings-with-launch-of-ethereum-and-solana-exchange-traded-products.html | E7: Release states platform exceeded $14B AUM.
A8: EEM issuer page | B8: EEM AUM / fee / holdings / benchmark | C8: AUM 2026-09-18; holdings 2026-09-17; fee current prospectus | D8: https://www.ishares.com/us/products/239637/ishares-msci-emerging-markets-etf | E8: AUM, holdings, fee, benchmark, inception. Field dates differ; see Product Landscape.
A9: IEMG issuer page | B9: IEMG AUM / fee / holdings / benchmark | C9: AUM 2026-09-18; holdings 2026-09-17; fee current prospectus | D9: https://www.ishares.com/us/products/244050/ishares-core-msci-emerging-markets-etf | E9: AUM, holdings, fee, benchmark, inception.
A10: VWO issuer page | B10: VWO AUM / fee / holdings / benchmark | C10: AUM 2026-08-31; holdings 2026-07-31; fee 2026-02-27 | D10: https://advisors.vanguard.com/investments/products/vwo/vanguard-ftse-emerging-markets-etf | E10: AUM, holdings, fee, benchmark, inception. Field dates differ.
A11: SPEM issuer page | B11: SPEM AUM / fee / holdings / benchmark | C11: AUM/holdings 2026-09-16; fund information/fee 2026-09-17 | D11: https://www.ssga.com/us/en/individual/etfs/state-street-spdr-portfolio-emerging-markets-etf-spem | E11: AUM, holdings, fee, benchmark, inception.
A12: SCHE issuer page | B12: SCHE AUM / fee / holdings / benchmark | C12: AUM 2026-09-18; holdings 2026-09-17; fee 0.06% effective 2026-06-11 | D12: https://www.schwabassetmanagement.com/products/sche | E12: AUM, holdings, fee, benchmark, inception.
A13: Historical Price Data
A14: SPY Digrin price history | B14: Month-end adjusted prices used in 3Y risk analysis | C14: Aug 2023–Aug 2026 | D14: https://www.digrin.com/stocks/detail/SPY/price | E14: Public monthly adjusted-price history; August 2026 used as final full month.
A15: QQQ Digrin price history | B15: Month-end adjusted prices used in 3Y risk analysis | C15: Aug 2023–Aug 2026 | D15: https://www.digrin.com/stocks/detail/QQQ/price | E15: Public monthly adjusted-price history; August 2026 used as final full month.
A16: IWM Digrin price history | B16: Month-end adjusted prices used in 3Y risk analysis | C16: Aug 2023–Aug 2026 | D16: https://www.digrin.com/stocks/detail/IWM/price | E16: Public monthly adjusted-price history; August 2026 used as final full month.
A17: EFA Digrin price history | B17: Month-end adjusted prices used in 3Y risk analysis | C17: Aug 2023–Aug 2026 | D17: https://www.digrin.com/stocks/detail/EFA/price | E17: Public monthly adjusted-price history; August 2026 used as final full month.
A18: EEM Digrin price history | B18: Month-end adjusted prices used in 3Y risk analysis | C18: Aug 2023–Aug 2026 | D18: https://www.digrin.com/stocks/detail/EEM/price | E18: Public monthly adjusted-price history; August 2026 used as final full month.
A19: AGG Digrin price history | B19: Month-end adjusted prices used in 3Y risk analysis | C19: Aug 2023–Aug 2026 | D19: https://www.digrin.com/stocks/detail/AGG/price | E19: Public monthly adjusted-price history; August 2026 used as final full month.
A20: LQD Digrin price history | B20: Month-end adjusted prices used in 3Y risk analysis | C20: Aug 2023–Aug 2026 | D20: https://www.digrin.com/stocks/detail/LQD/price | E20: Public monthly adjusted-price history; August 2026 used as final full month.
A21: HYG Digrin price history | B21: Month-end adjusted prices used in 3Y risk analysis | C21: Aug 2023–Aug 2026 | D21: https://www.digrin.com/stocks/detail/HYG/price | E21: Public monthly adjusted-price history; August 2026 used as final full month.
A22: GLD Digrin price history | B22: Month-end adjusted prices used in 3Y risk analysis | C22: Aug 2023–Aug 2026 | D22: https://www.digrin.com/stocks/detail/GLD/price | E22: Public monthly adjusted-price history; August 2026 used as final full month.
A23: VNQ Digrin price history | B23: Month-end adjusted prices used in 3Y risk analysis | C23: Aug 2023–Aug 2026 | D23: https://www.digrin.com/stocks/detail/VNQ/price | E23: Public monthly adjusted-price history; August 2026 used as final full month.
A24: FRED DGS3MO | B24: Monthly risk-free rate for Sharpe / Sortino excess returns | C24: Last available business-day observation each month, Sep 2023–Aug 2026; accessed 2026-09-19 | D24: https://fred.stlouisfed.org/series/DGS3MO | E24: Federal Reserve Board H.15 3-month Treasury constant-maturity yield. Exact observation date is shown on Risk-Free Rates; monthly equivalent derived as (1+annual yield)^(1/12)-1.
A26: Data audit note | B26: Historical-price snapshot verified against Digrin monthly adjusted-price tables; competitor fields verified against issuer pages; risk-free observations verified against FRED. | C26: Audit performed 2026-09-19 | D26: See data/source_manifest.csv and DATA_AUDIT.md in repository. | E26: Derived metrics are calculated from the bundled source files; they are not manually entered market statistics.
